{
    "keep": {
        "days": true,
        "amount": 14
    },
    "auditLog": "log\\.9e0e70c869af7dde0e9b3bd00cfb023c441e1c3d-audit.json",
    "files": [
        {
            "date": 1544394108354,
            "name": "log\\application-2018-12-09-16.log",
            "hash": "ecdbe94c8e7f0cd52568254b9340a65f"
        },
        {
            "date": 1544413591352,
            "name": "log\\application-2018-12-09-21.log",
            "hash": "8580ac7ac5b74c124c38b33aa80e13b4"
        },
        {
            "date": 1544463371143,
            "name": "log\\application-2018-12-10-11.log",
            "hash": "22f98cf751c2827eb1c2420eb8e0b937"
        },
        {
            "date": 1544465297586,
            "name": "log\\application-2018-12-10-12.log",
            "hash": "938fbde244ceb576a95f4e7a070cd443"
        },
        {
            "date": 1544476397547,
            "name": "log\\application-2018-12-10-15.log",
            "hash": "9a8cddd8c49f0170a3d8ea857cc6270c"
        },
        {
            "date": 1544496641210,
            "name": "log\\application-2018-12-10-20.log",
            "hash": "906ca04852889cffd34e682315e8ee12"
        }
    ]
}